tatt/__init__.py
tatt/config.py
tatt/exceptions.py
tatt/helpers.py
tatt/transcribe.py
tatt/tests/__init__.py
tatt/tests/test_amazon.py
tatt/tests/test_transcribe.py
tatt/tests/test_vendors.py
tatt/vendors/__init__.py
tatt/vendors/amazon.py
tatt/vendors/google.py
tatt/vendors/vendor.py
tatt-0.981.dist-info/LICENSE
tatt-0.981.dist-info/METADATA
tatt-0.981.dist-info/WHEEL
tatt-0.981.dist-info/entry_points.txt
tatt-0.981.dist-info/top_level.txt
tatt-0.981.dist-info/RECORD
