Metadata-Version: 2.1
Name: tatt
Version: 0.981
Summary: Tatt creates a uniform API for multiple speech-to-text (STT) services.
Home-page: https://github.com/zevaverbach/tatt
License: UNKNOWN
Platform: UNKNOWN
Requires-Dist: Click
Requires-Dist: awscli
Requires-Dist: boto3
Requires-Dist: requests
Requires-Dist: google-cloud-speech
Requires-Dist: audioread
Requires-Dist: google-cloud-storage
